skstyle_bot/__init__.py
skstyle_bot/__main__.py
skstyle_bot/comments
skstyle_bot/data_manager.py
skstyle_bot/email.py
skstyle_bot/order_handle.py
skstyle_bot-0.1.3.dist-info/entry_points.txt
skstyle_bot-0.1.3.dist-info/LICENSE
skstyle_bot-0.1.3.dist-info/WHEEL
skstyle_bot-0.1.3.dist-info/METADATA
skstyle_bot-0.1.3.dist-info/RECORD
