Metadata-Version: 2.1
Name: skstyle-bot
Version: 0.1.3
Summary: Selenium Bot for sstore admin panels
Author: kubaszpak
Author-email: jakub.szpak.it@gmail.com
Requires-Python: >=3.8,<4.0
Classifier: Programming Language :: Python :: 3
Classifier: Programming Language :: Python :: 3.8
Requires-Dist: pytest (>=5.4.3,<6.0.0)
Requires-Dist: selenium (>=3.141.0,<4.0.0)
